MANIFEST.in
README.rst
setup.py
docs/HISTORY.txt
docs/INSTALL.txt
docs/LICENSE.GPL
docs/LICENSE.txt
ftw/__init__.py
ftw.shop.egg-info/PKG-INFO
ftw.shop.egg-info/SOURCES.txt
ftw.shop.egg-info/dependency_links.txt
ftw.shop.egg-info/entry_points.txt
ftw.shop.egg-info/namespace_packages.txt
ftw.shop.egg-info/not-zip-safe
ftw.shop.egg-info/requires.txt
ftw.shop.egg-info/top_level.txt
ftw/shop/README.txt
ftw/shop/__init__.py
ftw/shop/btree_storage.py
ftw/shop/config.py
ftw/shop/configure.zcml
ftw/shop/default_status_set.py
ftw/shop/exceptions.py
ftw/shop/extender.py
ftw/shop/interfaces.py
ftw/shop/lawgiver.zcml
ftw/shop/mailer.py
ftw/shop/setuphandlers.py
ftw/shop/testing.py
ftw/shop/utils.py
ftw/shop/vocabularies.py
ftw/shop/browser/__init__.py
ftw/shop/browser/cart.py
ftw/shop/browser/cart.zcml
ftw/shop/browser/category.py
ftw/shop/browser/checkout.py
ftw/shop/browser/configure.zcml
ftw/shop/browser/controlpanel.py
ftw/shop/browser/initialize.py
ftw/shop/browser/mail.zcml
ftw/shop/browser/manage_categories.py
ftw/shop/browser/ordermanager.py
ftw/shop/browser/shopitem.py
ftw/shop/browser/supplier_mail.py
ftw/shop/browser/resources/16x16-add.png
ftw/shop/browser/resources/16x16-delete.png
ftw/shop/browser/resources/16x16-drag.png
ftw/shop/browser/resources/24x24-add.png
ftw/shop/browser/resources/24x24-delete.png
ftw/shop/browser/resources/addcart_p.gif
ftw/shop/browser/resources/contactform_prefill.js
ftw/shop/browser/resources/delete_p.gif
ftw/shop/browser/resources/edit_variations.js
ftw/shop/browser/resources/einzahlungsschein.png
ftw/shop/browser/resources/ftw_shop.css
ftw/shop/browser/resources/jquery-ui-i18n-manual.js
ftw/shop/browser/resources/onegov_integration.scss
ftw/shop/browser/resources/shop.js
ftw/shop/browser/resources/shop_config.js
ftw/shop/browser/resources/shop_price_calculation.js
ftw/shop/browser/templates/cart_edit.pt
ftw/shop/browser/templates/category.pt
ftw/shop/browser/templates/checkout-wizard.pt
ftw/shop/browser/templates/controlpanel.pt
ftw/shop/browser/templates/edit_categories.pt
ftw/shop/browser/templates/edit_variations.pt
ftw/shop/browser/templates/employee_number.pt
ftw/shop/browser/templates/order_manager.pt
ftw/shop/browser/templates/order_view.pt
