Metadata-Version: 1.1
Name: ftw.shop
Version: 3.0.1
Summary: A web shop solution for Plone
Home-page: https://github.com/4teamwork/ftw.shop
Author: 4teamwork AG
Author-email: mailto:info@4teamwork.ch
License: GPL2
Keywords: ftw shop plone
Platform: UNKNOWN
Classifier: Framework :: Plone
Classifier: Framework :: Plone :: 4.3
Classifier: Programming Language :: Python
Classifier: Topic :: Software Development :: Libraries :: Python Modules
